{ "compressionlevel":-1,
 "editorsettings":
    {
     "export":
        {
         "format":"json",
         "target":"house1.json"
        }
    },
 "height":15,
 "infinite":false,
 "layers":[
        {
         "data":[0, 0, 0, 0, 0, 0, 0, 0, 0, 0, 0, 0, 0, 0, 0, 0, 0, 0, 0, 0, 0, 26, 26, 26, 26, 26, 187, 187, 187, 0, 0, 26, 26, 26, 26, 26, 187, 187, 187, 0, 0, 26, 26, 26, 26, 26, 187, 187, 187, 0, 0, 26, 26, 26, 26, 26, 26, 26, 26, 0, 0, 871, 871, 871, 871, 871, 871, 875, 685, 0, 0, 871, 871, 871, 871, 871, 871, 875, 685, 0, 0, 875, 875, 875, 875, 875, 875, 875, 871, 0, 0, 871, 875, 875, 875, 875, 875, 871, 871, 0, 0, 871, 875, 875, 875, 875, 875, 871, 871, 0, 0, 871, 875, 875, 875, 875, 875, 871, 871, 0, 0, 26, 26, 26, 26, 2684354581, 26, 26, 26, 0, 0, 26, 26, 26, 26, 26, 26, 26, 26, 0, 0, 0, 0, 0, 0, 0, 0, 0, 0, 0],
         "height":15,
         "id":1,
         "name":"BaseLayer",
         "opacity":1,
         "properties":[
                {
                 "name":"isBackground",
                 "type":"bool",
                 "value":true
                }],
         "type":"tilelayer",
         "visible":true,
         "width":10,
         "x":0,
         "y":0
        }, 
        {
         "data":[0, 0, 0, 0, 0, 0, 0, 0, 0, 0, 0, 0, 0, 0, 0, 0, 0, 0, 0, 0, 0, 0, 0, 0, 0, 0, 0, 0, 0, 0, 0, 0, 0, 0, 0, 0, 0, 0, 0, 0, 0, 0, 0, 0, 0, 0, 0, 0, 0, 0, 0, 0, 0, 0, 0, 0, 0, 0, 0, 0, 0, 0, 0, 0, 0, 0, 0, 0, 0, 0, 0, 0, 662, 663, 664, 0, 0, 0, 0, 0, 0, 0, 0, 688, 689, 690, 0, 0, 0, 0, 0, 0, 0, 720, 721, 722, 0, 0, 0, 0, 0, 0, 687, 0, 0, 0, 0, 0, 0, 0, 0, 0, 719, 0, 0, 0, 0, 0, 0, 0, 0, 0, 751, 752, 753, 754, 755, 0, 0, 0, 0, 0, 0, 0, 0, 0, 0, 0, 0, 0, 0, 0, 0, 0, 0, 0, 0, 0, 0, 0],
         "height":15,
         "id":9,
         "name":"OnFloor",
         "opacity":1,
         "type":"tilelayer",
         "visible":true,
         "width":10,
         "x":0,
         "y":0
        }, 
        {
         "data":[2, 9, 9, 9, 9, 9, 9, 9, 9, 11, 137, 36, 38, 36, 36, 36, 38, 36, 36, 43, 66, 0, 0, 0, 0, 0, 0, 0, 0, 43, 137, 0, 0, 0, 0, 0, 0, 0, 0, 43, 137, 0, 0, 0, 0, 0, 0, 0, 0, 43, 137, 1611, 1611, 0, 0, 1614, 1614, 1614, 1614, 43, 137, 0, 0, 0, 0, 0, 0, 0, 0, 43, 137, 0, 0, 0, 0, 0, 0, 0, 0, 43, 137, 0, 0, 0, 0, 0, 0, 0, 0, 43, 137, 0, 0, 0, 0, 0, 0, 0, 0, 43, 137, 0, 0, 0, 0, 0, 0, 0, 0, 43, 137, 0, 0, 0, 0, 0, 0, 0, 0, 43, 147, 3221225843, 3221225843, 3221225651, 0, 147, 3221225843, 3221225843, 3221225843, 147, 147, 119, 119, 1610613119, 0, 2684354943, 119, 119, 119, 147, 147, 119, 119, 1610613119, 56, 2684354943, 119, 119, 119, 147],
         "height":15,
         "id":3,
         "name":"Walls",
         "opacity":1,
         "properties":[
                {
                 "name":"collides",
                 "type":"bool",
                 "value":true
                }],
         "type":"tilelayer",
         "visible":true,
         "width":10,
         "x":0,
         "y":0
        }, 
        {
         "data":[0, 0, 0, 0, 0, 0, 0, 0, 0, 0, 0, 0, 0, 0, 0, 0, 0, 0, 0, 0, 0, 67, 67, 67, 67, 67, 67, 67, 67, 0, 0, 0, 0, 0, 0, 0, 0, 0, 0, 0, 0, 1723, 1723, 0, 0, 1723, 1723, 1723, 1723, 0, 0, 0, 0, 0, 0, 0, 0, 0, 0, 0, 0, 0, 0, 0, 0, 0, 0, 0, 0, 0, 0, 0, 0, 0, 0, 0, 0, 0, 0, 0, 0, 0, 0, 0, 0, 0, 0, 0, 0, 0, 0, 0, 0, 0, 0, 0, 0, 0, 0, 0, 0, 0, 0, 0, 0, 0, 0, 0, 0, 0, 0, 0, 0, 0, 0, 0, 0, 0, 0, 0, 0, 0, 0, 0, 0, 0, 0, 0, 0, 0, 0, 0, 0, 0, 0, 0, 0, 0, 0, 0, 0, 0, 0, 0, 0, 0, 0, 0, 0, 0],
         "height":15,
         "id":5,
         "name":"WallsNoCollide",
         "opacity":1,
         "type":"tilelayer",
         "visible":true,
         "width":10,
         "x":0,
         "y":0
        }, 
        {
         "data":[2, 9, 9, 9, 9, 9, 9, 9, 9, 11, 0, 0, 301, 0, 0, 0, 301, 0, 0, 0, 0, 0, 0, 0, 0, 0, 0, 0, 0, 0, 0, 0, 0, 0, 0, 0, 0, 0, 0, 0, 0, 0, 0, 0, 0, 0, 0, 0, 0, 0, 0, 0, 0, 0, 0, 0, 0, 0, 0, 0, 0, 0, 0, 0, 0, 0, 0, 0, 0, 0, 0, 0, 0, 0, 0, 0, 0, 0, 0, 0, 0, 0, 0, 0, 0, 0, 0, 0, 0, 0, 0, 0, 0, 0, 0, 0, 0, 0, 0, 0, 0, 0, 0, 0, 0, 0, 0, 0, 0, 0, 0, 0, 0, 0, 0, 0, 0, 0, 0, 0, 0, 0, 0, 0, 0, 0, 0, 0, 0, 0, 0, 0, 0, 0, 0, 0, 0, 0, 0, 0, 0, 0, 0, 0, 0, 0, 0, 0, 0, 0],
         "height":15,
         "id":4,
         "name":"Curtains",
         "opacity":1,
         "type":"tilelayer",
         "visible":true,
         "width":10,
         "x":0,
         "y":0
        }, 
        {
         "data":[0, 0, 0, 0, 0, 0, 0, 0, 0, 0, 0, 2258, 0, 0, 2372, 2372, 0, 2381, 2382, 0, 0, 0, 0, 0, 2404, 2405, 2412, 2413, 2414, 0, 0, 2306, 0, 0, 0, 0, 0, 0, 0, 0, 0, 2338, 0, 0, 0, 0, 0, 0, 0, 0, 0, 0, 0, 0, 0, 0, 0, 0, 0, 0, 0, 2004, 2005, 0, 0, 0, 0, 0, 0, 0, 0, 1975, 2019, 0, 0, 0, 0, 626, 627, 0, 0, 1999, 0, 0, 0, 0, 0, 0, 0, 0, 0, 0, 0, 0, 0, 0, 0, 0, 0, 0, 0, 0, 0, 0, 0, 0, 0, 0, 2168, 0, 0, 0, 0, 0, 0, 0, 0, 0, 0, 0, 0, 0, 0, 0, 0, 0, 0, 0, 0, 0, 0, 0, 0, 0, 0, 0, 0, 0, 0, 0, 0, 0, 0, 0, 0, 0, 0, 0, 0, 0],
         "height":15,
         "id":2,
         "name":"Furniture",
         "opacity":1,
         "properties":[
                {
                 "name":"collides",
                 "type":"bool",
                 "value":true
                }],
         "type":"tilelayer",
         "visible":true,
         "width":10,
         "x":0,
         "y":0
        }, 
        {
         "data":[0, 0, 0, 0, 0, 0, 0, 0, 0, 0, 0, 0, 0, 0, 2072, 2117, 0, 2381, 2382, 0, 0, 0, 0, 0, 0, 0, 2412, 2413, 2414, 0, 0, 0, 0, 0, 0, 0, 0, 2445, 2446, 0, 0, 0, 0, 0, 0, 0, 0, 0, 0, 0, 0, 1980, 1981, 0, 0, 0, 0, 562, 563, 0, 0, 0, 0, 0, 0, 0, 0, 594, 0, 0, 0, 0, 0, 0, 0, 0, 0, 0, 0, 0, 0, 0, 0, 0, 0, 0, 0, 0, 0, 0, 0, 0, 0, 0, 0, 0, 0, 0, 0, 0, 0, 0, 0, 0, 0, 0, 0, 0, 0, 0, 0, 0, 0, 0, 0, 0, 0, 0, 0, 0, 0, 0, 0, 0, 0, 0, 0, 0, 0, 0, 0, 0, 0, 0, 0, 0, 0, 0, 0, 0, 0, 0, 0, 0, 0, 0, 0, 0, 0, 0],
         "height":15,
         "id":8,
         "name":"FurnitureNoCollide",
         "opacity":1,
         "type":"tilelayer",
         "visible":true,
         "width":10,
         "x":0,
         "y":0
        }, 
        {
         "draworder":"topdown",
         "id":6,
         "name":"Portals",
         "objects":[
                {
                 "height":0,
                 "id":2,
                 "name":"house1",
                 "point":true,
                 "properties":[
                        {
                         "name":"toScene",
                         "type":"string",
                         "value":"outdoors1"
                        }],
                 "rotation":0,
                 "type":"portal",
                 "visible":true,
                 "width":0,
                 "x":144.201210992082,
                 "y":452.724732184444
                }, 
                {
                 "height":0,
                 "id":5,
                 "name":"p.house1",
                 "point":true,
                 "properties":[
                        {
                         "name":"toScene",
                         "type":"string",
                         "value":"house1.upstairs"
                        }],
                 "rotation":0,
                 "type":"portal",
                 "visible":true,
                 "width":0,
                 "x":215.183977643223,
                 "y":240.33535165347
                }],
         "opacity":1,
         "type":"objectgroup",
         "visible":true,
         "x":0,
         "y":0
        }, 
        {
         "draworder":"topdown",
         "id":7,
         "name":"SpawnPoints",
         "objects":[
                {
                 "height":0,
                 "id":1,
                 "name":"house1",
                 "point":true,
                 "properties":[
                        {
                         "name":"fromScene",
                         "type":"string",
                         "value":"outdoors1"
                        }],
                 "rotation":0,
                 "type":"spawnPoint",
                 "visible":true,
                 "width":0,
                 "x":143.642291569632,
                 "y":408.570097810899
                }, 
                {
                 "height":0,
                 "id":3,
                 "name":"sp.house1",
                 "point":true,
                 "properties":[
                        {
                         "name":"fromScene",
                         "type":"string",
                         "value":"house1.upstairs"
                        }],
                 "rotation":0,
                 "type":"spawnPoint",
                 "visible":true,
                 "width":0,
                 "x":175.500698649278,
                 "y":240.33535165347
                }],
         "opacity":1,
         "properties":[
                {
                 "name":"fromScene",
                 "type":"string",
                 "value":"house1.upstairs"
                }],
         "type":"objectgroup",
         "visible":true,
         "x":0,
         "y":0
        }],
 "nextlayerid":10,
 "nextobjectid":6,
 "orientation":"orthogonal",
 "renderorder":"right-down",
 "tiledversion":"1.5.0",
 "tileheight":32,
 "tilesets":[
        {
         "columns":32,
         "firstgid":1,
         "image":"..\/tilesets\/houses_and_interiors2\/interiors.png",
         "imageheight":1024,
         "imagewidth":1024,
         "margin":0,
         "name":"interiors",
         "spacing":0,
         "tilecount":1024,
         "tileheight":32,
         "tilewidth":32
        }, 
        {
         "columns":22,
         "firstgid":1025,
         "image":"..\/tilesets\/houses_and_interiors\/houses_interriors.png",
         "imageheight":1280,
         "imagewidth":704,
         "margin":0,
         "name":"houses_interriors",
         "spacing":0,
         "tilecount":880,
         "tileheight":32,
         "tilewidth":32
        }, 
        {
         "columns":24,
         "firstgid":1905,
         "image":"..\/tilesets\/houses_and_interiors\/furnitures.png",
         "imageheight":384,
         "imagewidth":768,
         "margin":0,
         "name":"furnitures",
         "spacing":0,
         "tilecount":288,
         "tileheight":32,
         "tilewidth":32
        }, 
        {
         "columns":32,
         "firstgid":2193,
         "image":"..\/tilesets\/houses_and_interiors2\/furniture.png",
         "imageheight":256,
         "imagewidth":1024,
         "margin":0,
         "name":"furniture",
         "spacing":0,
         "tilecount":256,
         "tileheight":32,
         "tilewidth":32
        }],
 "tilewidth":32,
 "type":"map",
 "version":1.5,
 "width":10
}